deepanything/DeepAnythingClient.py
deepanything/ReasonClient.py
deepanything/ResponseClient.py
deepanything/Stream.py
deepanything/Utility.py
deepanything/__init__.py
deepanything/__main__.py
deepanything/metadatas.py
deepanything/Server/Server.py
deepanything/Server/Types.py
deepanything/Server/__init__.py
deepanything-0.1.9.dist-info/LICENSE
deepanything-0.1.9.dist-info/METADATA
deepanything-0.1.9.dist-info/WHEEL
deepanything-0.1.9.dist-info/entry_points.txt
deepanything-0.1.9.dist-info/top_level.txt
deepanything-0.1.9.dist-info/RECORD
