Metadata-Version: 2.1
Name: deepanything
Version: 0.1.9
Summary: DeepAnything is a project that provides DeepSeek R1's deep thinking capabilities for various large language models (LLMs).
Author: Junity
Author-email: 1727636624@qq.com
Classifier: Programming Language :: Python :: 3
Classifier: License :: OSI Approved :: MIT License
Classifier: Operating System :: OS Independent
License-File: LICENSE
Requires-Dist: openai
Requires-Dist: uvicorn
Requires-Dist: attrs
Requires-Dist: fastapi
Requires-Dist: pydantic
Requires-Dist: setuptools
